[
  {
    "username": "aasimkhan_ak46"
  },
  {
    "username": "hrishikesh__p"
  },
  {
    "username": "adnan_rajput_1_"
  },
  {
    "username": "jam_mustu18"
  },
  {
    "username": "bhargav5356"
  },
  {
    "username": "paras_sutar777"
  },
  {
    "username": "iaveshh"
  },
  {
    "username": "_.ken1218._"
  },
  {
    "username": "_____aniket_"
  },
  {
    "username": "chiragrana8888"
  },
  {
    "username": "appy_fizz_me"
  },
  {
    "username": "ayy_u_sshhh"
  },
  {
    "username": "shreyas.xviii_"
  },
  {
    "username": "brandon.b.ferns"
  },
  {
    "username": "ankit_dhumale_1222"
  },
  {
    "username": "siddhrajjsinh"
  },
  {
    "username": "neha_khannn__"
  },
  {
    "username": "amitapatil_30"
  },
  {
    "username": "anujsharma031"
  },
  {
    "username": "tanvi.abdagire"
  },
  {
    "username": "sirilaby"
  },
  {
    "username": "akshay_sose"
  },
  {
    "username": "itsaliakbar"
  },
  {
    "username": "comprehensivedesignservice"
  },
  {
    "username": "sanobarmotiwala"
  },
  {
    "username": "bakers.box_"
  },
  {
    "username": "sherozaldah"
  },
  {
    "username": "labdhi_chandaliya"
  },
  {
    "username": "manvichandaliya_"
  },
  {
    "username": "fauziyanoor"
  },
  {
    "username": "akif_9959"
  },
  {
    "username": "chinnu.25111"
  },
  {
    "username": "rotaract_pimpri"
  },
  {
    "username": "laughter_virus_"
  },
  {
    "username": "howra705"
  },
  {
    "username": "flykamshet_paragliding"
  },
  {
    "username": "bhookhahoon"
  },
  {
    "username": "sketchesandsplashes"
  },
  {
    "username": "lafiesta_viman_nagar"
  },
  {
    "username": "thefirstcopyshop"
  },
  {
    "username": "pune.jungle.safari"
  },
  {
    "username": "meenaaaaaz"
  },
  {
    "username": "foodiewizards"
  },
  {
    "username": "_chaaya.26_"
  },
  {
    "username": "_gulnaz_909"
  },
  {
    "username": "moomin_.7"
  },
  {
    "username": "al_thafif"
  },
  {
    "username": "rohitacharya16"
  },
  {
    "username": "iffat_yt"
  },
  {
    "username": "ziauddin_aod"
  },
  {
    "username": "anumazing_diaries"
  },
  {
    "username": "roger_thegoldenboy"
  },
  {
    "username": "radhachande_11"
  },
  {
    "username": "nadeem_shaikh1234"
  },
  {
    "username": "ayeshahahahahahaha"
  },
  {
    "username": "m_a_i_r_a_k_h_a_n_01"
  },
  {
    "username": "tamannaaa_09"
  },
  {
    "username": "movie_quotes_dialogues"
  },
  {
    "username": "x_smarty_boi__akko"
  },
  {
    "username": "sai_lonkar_777"
  },
  {
    "username": "awwab_salim"
  },
  {
    "username": "afridikhan_9"
  },
  {
    "username": "simar_2607"
  },
  {
    "username": "rashed_shaik"
  },
  {
    "username": "omkar_sinalkar"
  },
  {
    "username": "_teetucker_"
  },
  {
    "username": "smarty_sammy_26"
  },
  {
    "username": "micku_parth23"
  },
  {
    "username": "arshiasayed0911"
  },
  {
    "username": "mrakashdagade98"
  },
  {
    "username": "prerna_kadam_"
  },
  {
    "username": "vishal_kamthe"
  },
  {
    "username": "arjunkhandelwal04"
  },
  {
    "username": "junaid2552"
  },
  {
    "username": "deenireminders"
  },
  {
    "username": "patelmehvish"
  },
  {
    "username": "samruddhi.nate"
  },
  {
    "username": "sayfais"
  },
  {
    "username": "sourabh_shelke"
  },
  {
    "username": "ay_baddo_"
  },
  {
    "username": "altamash.shaikh9"
  },
  {
    "username": "khotwasim"
  },
  {
    "username": "gudakuwalaaquif"
  },
  {
    "username": "saadutansari"
  },
  {
    "username": "ilham1.5"
  },
  {
    "username": "mrunmay.24"
  },
  {
    "username": "labina.syd"
  },
  {
    "username": "sahilsayyed513"
  },
  {
    "username": "_khan.farheen"
  },
  {
    "username": "caprineagrotech"
  },
  {
    "username": "itsemraann"
  },
  {
    "username": "rahat_shaikh___"
  },
  {
    "username": "med__tour"
  },
  {
    "username": "___despicable___me___"
  },
  {
    "username": "_aakashanks_"
  },
  {
    "username": "matmaxmusic"
  },
  {
    "username": "moresachin1996"
  },
  {
    "username": "faraz_kr"
  },
  {
    "username": "mohit_.shah"
  },
  {
    "username": "papdeja_59_fcca"
  },
  {
    "username": "wordsinwards"
  },
  {
    "username": "_harsharai_"
  },
  {
    "username": "heera.nawab.98"
  },
  {
    "username": "chandlenajeeb"
  },
  {
    "username": "sagar452"
  },
  {
    "username": "babubha1"
  },
  {
    "username": "anjumanpatel"
  },
  {
    "username": "minichoudhury"
  },
  {
    "username": "kaavya_ki_kalam_se"
  },
  {
    "username": "mridul_saini"
  },
  {
    "username": "thepurplestardust"
  },
  {
    "username": "inside_azamsworld"
  },
  {
    "username": "sanyuja_chaudhari"
  },
  {
    "username": "kh.u.lood"
  },
  {
    "username": "utkarshdave7"
  },
  {
    "username": "rva_2097"
  },
  {
    "username": "eat_pray_dream_repeat"
  },
  {
    "username": "singh_shivangini"
  },
  {
    "username": "_rutuja.ghule_"
  },
  {
    "username": "kfarheen450"
  },
  {
    "username": "jr_jr_loki"
  },
  {
    "username": "pr1ncesa__"
  },
  {
    "username": "portraitsofpersonalities"
  },
  {
    "username": "fanpage_dooll"
  },
  {
    "username": "ykapadia111"
  },
  {
    "username": "elvej21"
  },
  {
    "username": "zhelheart"
  },
  {
    "username": "maazkazi7"
  },
  {
    "username": "aikyab4u"
  },
  {
    "username": "ubaidmundewadi"
  },
  {
    "username": "sunny_is_a_good_name"
  },
  {
    "username": "abhijeet_dhillon"
  },
  {
    "username": "spices.wagon"
  },
  {
    "username": "alijensen644"
  },
  {
    "username": "omkar_zende96k"
  },
  {
    "username": "v2511ps"
  },
  {
    "username": "varuna_hiraskar"
  },
  {
    "username": "halamthings"
  },
  {
    "username": "_notequote__"
  },
  {
    "username": "theartcloud__"
  },
  {
    "username": "happiness.is.chocolates"
  },
  {
    "username": "shreelachauhan"
  },
  {
    "username": "riza.shaikh06"
  },
  {
    "username": "rehanadthe"
  },
  {
    "username": "shagufamomin70"
  },
  {
    "username": "darshangundecha"
  },
  {
    "username": "shubhamkamthe22"
  },
  {
    "username": "__love_allah_"
  },
  {
    "username": "mudassir_chougule"
  },
  {
    "username": "wasimkothiwale"
  },
  {
    "username": "waheeda.tabassum"
  },
  {
    "username": "hainahena"
  },
  {
    "username": "sunilsagar8085"
  },
  {
    "username": "harambiryanii"
  },
  {
    "username": "paaatriiiiiciaaaa"
  },
  {
    "username": "_bhookswings_"
  },
  {
    "username": "tota99f"
  },
  {
    "username": "amaan_qadri_1"
  },
  {
    "username": "lost._soul__"
  },
  {
    "username": "mehnaz_909"
  },
  {
    "username": "chede98"
  },
  {
    "username": "0rq7"
  },
  {
    "username": "officail_____"
  },
  {
    "username": "arpita_limbane"
  },
  {
    "username": "selfthinkings"
  },
  {
    "username": "syedambreen_"
  },
  {
    "username": "umaidpandit"
  },
  {
    "username": "gayatri.nayal"
  },
  {
    "username": "ar______allauddin____78666"
  },
  {
    "username": "it_me_smarty_boy"
  },
  {
    "username": "hazzyyyy_d"
  },
  {
    "username": "saachi_sb12"
  },
  {
    "username": "shubhamjangid7"
  },
  {
    "username": "starfood.official"
  },
  {
    "username": "hani_seher"
  },
  {
    "username": "yasmeen__khan__"
  },
  {
    "username": "__aftab02"
  },
  {
    "username": "anjum8139"
  },
  {
    "username": "habibi_sheesha_lounge"
  },
  {
    "username": "damello_lara007"
  },
  {
    "username": "ibrahim.inamdar.7311"
  },
  {
    "username": "hjhj.98"
  },
  {
    "username": "path_996"
  },
  {
    "username": "shivanisakharkar_offical"
  },
  {
    "username": "mr________ehan_25"
  },
  {
    "username": "asifnizami"
  },
  {
    "username": "sam__8085__"
  },
  {
    "username": "querencia_elysian"
  },
  {
    "username": "foodieecrush88"
  },
  {
    "username": "tarannumaltafshaikh"
  },
  {
    "username": "mushuuu_06"
  },
  {
    "username": "mayurii_i"
  },
  {
    "username": "abrar.memon_"
  },
  {
    "username": "sumaiya.shaikhu"
  },
  {
    "username": "akriti_nigam_srivastava"
  },
  {
    "username": "nada_khaled52"
  },
  {
    "username": "dulgajkunal24"
  },
  {
    "username": "khubaibshake"
  },
  {
    "username": "the_amya"
  },
  {
    "username": "psychotic_steer"
  },
  {
    "username": "shifansarii"
  },
  {
    "username": "sanuaps1"
  },
  {
    "username": "mamtasomvanshi"
  },
  {
    "username": "borkaaan.___"
  },
  {
    "username": "aasma.shaikh.75"
  },
  {
    "username": "basherdilbar"
  },
  {
    "username": "beebztagram"
  },
  {
    "username": "nilofarnawab"
  },
  {
    "username": "vinitha_muralidharan"
  },
  {
    "username": "shaikh_7_8_6_0_"
  },
  {
    "username": "uzmakhanb"
  },
  {
    "username": "himanshu.__"
  },
  {
    "username": "t_ashish_"
  },
  {
    "username": "chetandeo_7"
  },
  {
    "username": "zahabiya_saeed"
  },
  {
    "username": "zagg_sheikh"
  },
  {
    "username": "pranit.05"
  },
  {
    "username": "giri_on_fire"
  },
  {
    "username": "id_himan"
  },
  {
    "username": "preciously__me"
  },
  {
    "username": "aaaksh27"
  },
  {
    "username": "rashmidshinde"
  },
  {
    "username": "deepthipoduval"
  },
  {
    "username": "dannydman007"
  },
  {
    "username": "mithila_meher"
  },
  {
    "username": "_manisha_gawade"
  },
  {
    "username": "_rashmipatil_"
  },
  {
    "username": "pranu_1603"
  },
  {
    "username": "shreyaaaaaa_nahar"
  },
  {
    "username": "piyush_savadekar"
  },
  {
    "username": "mangesh___09"
  },
  {
    "username": "farooquisana16"
  },
  {
    "username": "sh._.ruti"
  },
  {
    "username": "harshali_waghile"
  },
  {
    "username": "yasser_kazi_"
  },
  {
    "username": "iampranoti"
  },
  {
    "username": "mullaomar"
  },
  {
    "username": "shaikhs371"
  },
  {
    "username": "yazzi_11"
  },
  {
    "username": "shakktimaan"
  },
  {
    "username": "darshan_pable"
  },
  {
    "username": "vipul_kagle"
  },
  {
    "username": "_shubham_d"
  },
  {
    "username": "aashay_patil"
  },
  {
    "username": "nikhhhaaattt"
  },
  {
    "username": "priya_mandhare"
  },
  {
    "username": "_ashish.07"
  },
  {
    "username": "pia_d28"
  },
  {
    "username": "the_sneha_das_"
  },
  {
    "username": "anjali_m_25"
  },
  {
    "username": "karan21_g"
  },
  {
    "username": "gauri_697"
  },
  {
    "username": "shivuhole"
  },
  {
    "username": "komal_sonavane_"
  },
  {
    "username": "_.pradnya.kadlag._"
  },
  {
    "username": "mustkim_maniyar"
  },
  {
    "username": "digvijaydevkar"
  },
  {
    "username": "kiran__more"
  },
  {
    "username": "burhanalwala"
  },
  {
    "username": "deshmukh.abdul.k"
  },
  {
    "username": "ashu1598"
  },
  {
    "username": "shahparshiv"
  },
  {
    "username": "md_saaddd"
  },
  {
    "username": "_yaseen_desai_"
  },
  {
    "username": "aniket_7172"
  },
  {
    "username": "anikets.wankhede"
  },
  {
    "username": "nirhali_nikita"
  },
  {
    "username": "deepali_shinde11"
  },
  {
    "username": "vvirajj"
  },
  {
    "username": "_danny97__"
  },
  {
    "username": "adik_tetgure"
  },
  {
    "username": "satyamdode"
  },
  {
    "username": "susi_vela45"
  },
  {
    "username": "ruturaj_7997"
  },
  {
    "username": "mehnaaz_anwar"
  },
  {
    "username": "shub_1301"
  },
  {
    "username": "giru.rathi97"
  },
  {
    "username": "prettyinthedark____"
  },
  {
    "username": "samreensayed"
  },
  {
    "username": "rakesh_prabhu1"
  },
  {
    "username": "farrrheeen"
  },
  {
    "username": "sahil__2257"
  },
  {
    "username": "heartcarvingsss"
  },
  {
    "username": "shripad99"
  },
  {
    "username": "mayuri_s_c"
  },
  {
    "username": "pisekrupa"
  },
  {
    "username": "zainab_warsi_"
  },
  {
    "username": "fahaddsayyad"
  },
  {
    "username": "tejasvibopinwar"
  },
  {
    "username": "tierra_guerrero_98"
  },
  {
    "username": "aakaash_patilzz"
  },
  {
    "username": "navweein"
  },
  {
    "username": "an__i__ket"
  },
  {
    "username": "wrdljwry414"
  },
  {
    "username": "patil.darshan_"
  },
  {
    "username": "sourav3006"
  },
  {
    "username": "unashamedly_perfect"
  },
  {
    "username": "ramz.rafique"
  },
  {
    "username": "chetan.twelve"
  },
  {
    "username": "aishwarya_borde"
  },
  {
    "username": "akashsurwase97"
  },
  {
    "username": "ambika2034"
  },
  {
    "username": "cadet_forever"
  },
  {
    "username": "anisha_sonawle"
  },
  {
    "username": "jayant.waghmare"
  },
  {
    "username": "shitij_patel"
  },
  {
    "username": "sahil_memon_"
  },
  {
    "username": "heena_chavan1298"
  },
  {
    "username": "dakumemes"
  },
  {
    "username": "_zayd21_"
  },
  {
    "username": "saquib_29"
  },
  {
    "username": "afsha_shaikh_"
  },
  {
    "username": "rafi_shagir"
  },
  {
    "username": "akashdagade_ad"
  },
  {
    "username": "sahil_shk"
  },
  {
    "username": "gaurav_ursal3888"
  },
  {
    "username": "daniyaaaaaaaa___"
  },
  {
    "username": "mamtaatole"
  },
  {
    "username": "aniket_4407"
  },
  {
    "username": "sourabh.gaikwad"
  },
  {
    "username": "shaikh_nawaz121"
  },
  {
    "username": "_sanketg_"
  },
  {
    "username": "binda_kandola"
  },
  {
    "username": "bavarian.70"
  },
  {
    "username": "ayaan_khot"
  },
  {
    "username": "rajputnursery_"
  },
  {
    "username": "iabhishektagad"
  },
  {
    "username": "jocelynabn"
  },
  {
    "username": "farrel_barboza"
  },
  {
    "username": "pkaustubh007"
  },
  {
    "username": "pavelalam30"
  },
  {
    "username": "_itz___arsuu_"
  },
  {
    "username": "ali_patel303"
  },
  {
    "username": "_.in.a.flash._"
  },
  {
    "username": "aisha.kaif"
  },
  {
    "username": "abo_toh"
  },
  {
    "username": "cc.coffeeconnect"
  },
  {
    "username": "asha_jesudas"
  },
  {
    "username": "hashimsheikh__"
  },
  {
    "username": "sagar_29_"
  },
  {
    "username": "ali_aint_smiling"
  },
  {
    "username": "thefashion.trendz"
  },
  {
    "username": "owaisskhaaaan"
  },
  {
    "username": "saiekhude"
  },
  {
    "username": "fit.desire"
  },
  {
    "username": "maazin7"
  },
  {
    "username": "shubham_londave_2025"
  },
  {
    "username": "architganorkar"
  },
  {
    "username": "rushikeshsantre"
  },
  {
    "username": "rachit_taide"
  },
  {
    "username": "sakshigarg887"
  },
  {
    "username": "sanaa.iftikhar"
  },
  {
    "username": "roshannnnnnn"
  },
  {
    "username": "kulkarniparthh"
  },
  {
    "username": "ashraf_alolafy"
  },
  {
    "username": "manav_dodiya"
  },
  {
    "username": "fashion_select_hub"
  },
  {
    "username": "casualquartz"
  },
  {
    "username": "faisal3_3_97"
  },
  {
    "username": "nikkachui"
  },
  {
    "username": "imdf1"
  },
  {
    "username": "_faizanshaikh_fs"
  },
  {
    "username": "adityaa_gavali"
  },
  {
    "username": "asma_shahid_kazi"
  },
  {
    "username": "al_raeai"
  },
  {
    "username": "huzefa_haveli"
  },
  {
    "username": "__swaroop__"
  },
  {
    "username": "maheer_shaikh_"
  },
  {
    "username": "anumnawab"
  },
  {
    "username": "rohan_babar70"
  },
  {
    "username": "shagufta.imran.sayed"
  },
  {
    "username": "carmelities"
  },
  {
    "username": "mayurbadhe_777"
  },
  {
    "username": "sharukh_bhure"
  },
  {
    "username": "tasaufbhure_"
  },
  {
    "username": "jmalencase"
  },
  {
    "username": "vegeta_rd_"
  },
  {
    "username": "amuu_16"
  },
  {
    "username": "mushirakhan"
  },
  {
    "username": "rumana_003"
  },
  {
    "username": "kunalpurswani_"
  },
  {
    "username": "tati.0695"
  },
  {
    "username": "greeshmaagarwal"
  },
  {
    "username": "heba.tamim96"
  },
  {
    "username": "v.r.iyer"
  },
  {
    "username": "gesawat_aakib"
  },
  {
    "username": "_.riticulous._"
  },
  {
    "username": "ruban_sayyed"
  },
  {
    "username": "chubby_cheeks_venu"
  },
  {
    "username": "mohsin_shaikh_official"
  },
  {
    "username": "baebu2017"
  },
  {
    "username": "_saniashaikh"
  },
  {
    "username": "hrane19"
  },
  {
    "username": "masoudkhtib"
  },
  {
    "username": "noorfatima_31"
  },
  {
    "username": "itsyuvraj"
  },
  {
    "username": "shabnam_inamdar"
  },
  {
    "username": "emperius"
  },
  {
    "username": "amanshaikh6786"
  },
  {
    "username": "_diaa_08"
  },
  {
    "username": "_____shraddha___"
  },
  {
    "username": "squareinch_archi_interiordesgn"
  },
  {
    "username": "jamadarsalman"
  },
  {
    "username": "mdjunaid.k"
  },
  {
    "username": "alice_desouza_111"
  },
  {
    "username": "mr_perfect_saifu"
  },
  {
    "username": "khansflavour"
  },
  {
    "username": "iam_samujjal"
  },
  {
    "username": "___sara___37"
  },
  {
    "username": "headshot_undri"
  },
  {
    "username": "heart_runs_free"
  },
  {
    "username": "luwibianca"
  },
  {
    "username": "siddiqui_saleha"
  },
  {
    "username": "af_kh_as_sh"
  },
  {
    "username": "ace.clicks"
  },
  {
    "username": "sameer_shaikh_6622"
  },
  {
    "username": "sharuk_pathan_srk"
  },
  {
    "username": "hashtaghotsquad"
  },
  {
    "username": "shehbaaz0008"
  },
  {
    "username": "rajratan1985"
  },
  {
    "username": "__sameee_khan__"
  },
  {
    "username": "sonu.k14292"
  },
  {
    "username": "ramiza8051"
  },
  {
    "username": "misbahshaikh__"
  },
  {
    "username": "ariyan___marjan"
  },
  {
    "username": "aliaaxbhattx"
  },
  {
    "username": "techtr3nds"
  },
  {
    "username": "_kashish.verma_"
  },
  {
    "username": "ammieraj111"
  },
  {
    "username": "m3g2g"
  },
  {
    "username": "m_moin__"
  },
  {
    "username": "aakanksha_mua"
  },
  {
    "username": "_furkan__kaya_"
  },
  {
    "username": "rajeshchoudhary.47"
  },
  {
    "username": "yafay9"
  },
  {
    "username": "dinesh_choudhary_64"
  },
  {
    "username": "heame_ahmed"
  },
  {
    "username": "ho6zs"
  },
  {
    "username": "18beomay"
  },
  {
    "username": "paradoxical_chica"
  },
  {
    "username": "fali.gujjar"
  },
  {
    "username": "mustafaghee"
  },
  {
    "username": "nadiiiaaaaa._"
  },
  {
    "username": "thecactusgirl"
  },
  {
    "username": "nakulmuley"
  },
  {
    "username": "iikhizarshaikhii"
  },
  {
    "username": "sapreshruti"
  },
  {
    "username": "fariyaz_khan_02"
  },
  {
    "username": "saif.sayyed.9"
  },
  {
    "username": "akki_barod"
  },
  {
    "username": "rajendra_gaikwad05"
  },
  {
    "username": "khanderao.kamble.94"
  },
  {
    "username": "mohdbilalchaparaband"
  },
  {
    "username": "care_base_placement"
  },
  {
    "username": "moh_alaghbari"
  },
  {
    "username": "oves313"
  },
  {
    "username": "wattaword"
  },
  {
    "username": "__25__25___"
  },
  {
    "username": "sr.9858205678"
  },
  {
    "username": "farazsayed45"
  },
  {
    "username": "pragati_said"
  },
  {
    "username": "adv._hafsha_shaikh"
  },
  {
    "username": "isha_shete"
  },
  {
    "username": "fauzanthokan_"
  },
  {
    "username": "sarah_nawab"
  },
  {
    "username": "swapnilmungi"
  },
  {
    "username": "yaseen5shaikh"
  },
  {
    "username": "tualha_bin_abrar"
  },
  {
    "username": "aditi.anand.kurhade"
  },
  {
    "username": "50_shades__of_awesome_108"
  },
  {
    "username": "chi5758"
  },
  {
    "username": "rj.rumelkhan67"
  },
  {
    "username": "xx_rujul_xx"
  },
  {
    "username": "humpakistani"
  },
  {
    "username": "breathless_gal"
  },
  {
    "username": "followback3069"
  },
  {
    "username": "pitri9234"
  },
  {
    "username": "pratikingz"
  },
  {
    "username": "glory_rodriks"
  },
  {
    "username": "__digvijay_nalage_patil"
  },
  {
    "username": "saln_12"
  },
  {
    "username": "mzmolly79"
  },
  {
    "username": "krishna_sadavarte"
  },
  {
    "username": "saurabh_sr7"
  },
  {
    "username": "irssv"
  },
  {
    "username": "sush_patankar"
  },
  {
    "username": "dangerous1a"
  },
  {
    "username": "nawazbhai_"
  },
  {
    "username": "omkar_mangalgiri"
  },
  {
    "username": "its.ryan47"
  },
  {
    "username": "ammarakhan536"
  },
  {
    "username": "umairkhan1346"
  },
  {
    "username": "yogeshdahiya76"
  },
  {
    "username": "officialliferelatables"
  },
  {
    "username": "gentlemaninblack"
  },
  {
    "username": "sayed_arshiya11"
  },
  {
    "username": "f.a.c._photography"
  },
  {
    "username": "hashim8805"
  },
  {
    "username": "zii_9204"
  },
  {
    "username": "message.services.1"
  },
  {
    "username": "s.n_butt"
  },
  {
    "username": "its_me_shake_1795"
  },
  {
    "username": "shaikh7609"
  },
  {
    "username": "bad_boy1720"
  },
  {
    "username": "papa_tang0"
  },
  {
    "username": "nishant_pawar__"
  },
  {
    "username": "rosiebanerjee"
  },
  {
    "username": "aqibmalikawan"
  },
  {
    "username": "sameenshaikh130"
  },
  {
    "username": "vaibhavbajpai_"
  },
  {
    "username": "aaffy_gym_lover"
  },
  {
    "username": "aliabhatt_cutiiepie"
  },
  {
    "username": "c__aiqaz"
  },
  {
    "username": "aakashmadki_1997"
  },
  {
    "username": "jamal_shadab"
  },
  {
    "username": "dnyanashree_patil"
  },
  {
    "username": "always__caffeinated"
  },
  {
    "username": "prem.oswal18"
  },
  {
    "username": "affy_gym_lover"
  },
  {
    "username": "black_eyes_2_dimples"
  },
  {
    "username": "virago_09"
  },
  {
    "username": "vikey7865"
  },
  {
    "username": "saurabhkalbande"
  },
  {
    "username": "anto_soni64"
  },
  {
    "username": "jayeshd_gaikwad"
  },
  {
    "username": "shashank_temburni"
  },
  {
    "username": "yourusualpapadlover"
  },
  {
    "username": "muttanna07_"
  },
  {
    "username": "tvs_11.6"
  },
  {
    "username": "catl7453"
  },
  {
    "username": "swapnilkuwad"
  },
  {
    "username": "flying4miles555"
  },
  {
    "username": "aniket.kamthe7"
  },
  {
    "username": "kuchu_thecat"
  },
  {
    "username": "vineet_kasbe"
  },
  {
    "username": "arsalan6255"
  },
  {
    "username": "_shraddha_shinde_"
  },
  {
    "username": "____sad_ique"
  },
  {
    "username": "surbhi_agrawal8"
  },
  {
    "username": "nabeel6183"
  },
  {
    "username": "eadhunath"
  },
  {
    "username": "ak.romn"
  },
  {
    "username": "mateen_s_"
  },
  {
    "username": "ayaun_khan_0"
  },
  {
    "username": "m_promee"
  },
  {
    "username": "kn.mohammad"
  },
  {
    "username": "german_280"
  },
  {
    "username": "ac21_kc20"
  },
  {
    "username": "abdulazimshaikh"
  },
  {
    "username": "amani_miya"
  },
  {
    "username": "kuchipoothecat"
  },
  {
    "username": "_panda_025"
  },
  {
    "username": "sufiyanmokashi76"
  },
  {
    "username": "rehana.ts"
  },
  {
    "username": "prasannasonu"
  },
  {
    "username": "afreen_thaim"
  },
  {
    "username": "gabbar_is_back72"
  },
  {
    "username": "dxs_"
  },
  {
    "username": "anjusingaram"
  },
  {
    "username": "noranna_1972"
  },
  {
    "username": "sandy_26jan1987"
  },
  {
    "username": "sohail_6942"
  },
  {
    "username": "shaikhnazim_97"
  },
  {
    "username": "ronaldoserena"
  },
  {
    "username": "branded_kamini_alisha"
  },
  {
    "username": "good_hot_girls_12"
  },
  {
    "username": "bad_rule_sean"
  },
  {
    "username": "assimshaikh"
  },
  {
    "username": "jamilakhadpawala"
  },
  {
    "username": "hercoglife"
  },
  {
    "username": "lifestylelush0"
  },
  {
    "username": "kuuli1020"
  },
  {
    "username": "singh_lokdeep08"
  },
  {
    "username": "bd8803"
  },
  {
    "username": "snehal_s_5550"
  },
  {
    "username": "_rahul_gavhane_"
  },
  {
    "username": "khosyiyah"
  },
  {
    "username": "baloochamjad"
  },
  {
    "username": "chanteezsa"
  },
  {
    "username": "s_h_e_r_o_z"
  },
  {
    "username": "i_anjellina_ankita"
  },
  {
    "username": "_afreen_777_._"
  },
  {
    "username": "ineffablesuits"
  },
  {
    "username": "trolls_drug"
  },
  {
    "username": "shwrhh9737"
  },
  {
    "username": "swagg.fashion"
  },
  {
    "username": "cars_done_right"
  },
  {
    "username": "s_tazeen"
  },
  {
    "username": "mozzarlailaa"
  },
  {
    "username": "shubham_jadhav11"
  },
  {
    "username": "ali805548"
  },
  {
    "username": "ismail_karbari"
  },
  {
    "username": "mangesh__k"
  },
  {
    "username": "gopakumar.k.g"
  },
  {
    "username": "i_abu101"
  },
  {
    "username": "abdo.atef"
  },
  {
    "username": "nottuusedaanymore"
  },
  {
    "username": "janvi77777"
  },
  {
    "username": "soham_parab"
  },
  {
    "username": "aden_hora_"
  },
  {
    "username": "zaeem.alsham"
  },
  {
    "username": "s_rubeen"
  },
  {
    "username": "andy_demon8421"
  },
  {
    "username": "_.betweenpages"
  },
  {
    "username": "ismailphysio"
  },
  {
    "username": "11.04.15_"
  },
  {
    "username": "royal_buddys_shootout"
  },
  {
    "username": "rasha_rash0oz"
  },
  {
    "username": "ronald_999_007"
  },
  {
    "username": "sudhirnagarlg"
  },
  {
    "username": "tukang_sablon17"
  },
  {
    "username": "sanober_nawab"
  },
  {
    "username": "mlpresident"
  },
  {
    "username": "iam_jennifer_"
  },
  {
    "username": "ganesh_yewale_1215"
  },
  {
    "username": "h_herlina12"
  },
  {
    "username": "abdullaahmed.bh1"
  },
  {
    "username": "tamit56"
  },
  {
    "username": "juuzen_30"
  },
  {
    "username": "aman9711"
  },
  {
    "username": "rksanwaliya"
  },
  {
    "username": "anacmariac"
  },
  {
    "username": "ishita6477"
  },
  {
    "username": "amster1311"
  },
  {
    "username": "rajansidhurr"
  },
  {
    "username": "meninclass_official_page"
  },
  {
    "username": "rahmatoulaye80"
  },
  {
    "username": "atreya1997"
  },
  {
    "username": "yash_the_rockstar"
  },
  {
    "username": "07slim_shady_lp"
  },
  {
    "username": "aziz_bin_abdul"
  },
  {
    "username": "tamir104"
  },
  {
    "username": "a_i_s_h_a_c_h_a_t_t_e_r_j_e_e"
  },
  {
    "username": "savan_sutariya"
  },
  {
    "username": "lhom_kz"
  },
  {
    "username": "arohijannat1995"
  },
  {
    "username": "nokiasony495"
  },
  {
    "username": "krakhi"
  },
  {
    "username": "preetitomar290"
  },
  {
    "username": "aulakhsonu8"
  },
  {
    "username": "yasmine_ouchha"
  },
  {
    "username": "manunpuiikhawlhring"
  },
  {
    "username": "pher1818"
  },
  {
    "username": "milan.chavda4025"
  },
  {
    "username": "ik123344"
  },
  {
    "username": "karansingh456"
  },
  {
    "username": "rasakrangattor"
  },
  {
    "username": "f.s.rr.d"
  },
  {
    "username": "ashish.singhchauhan342"
  },
  {
    "username": "kashyabch"
  },
  {
    "username": "shamsuddinfeni"
  },
  {
    "username": "oye_vishu"
  },
  {
    "username": "vikram_indal_india"
  },
  {
    "username": "rahilstar7"
  },
  {
    "username": "christinamboyi"
  },
  {
    "username": "munna.rahman"
  },
  {
    "username": "jaypatil26295"
  },
  {
    "username": "kavya8806"
  },
  {
    "username": "adnan.azam"
  },
  {
    "username": "vishnuvenugopal"
  },
  {
    "username": "rak_aa123"
  },
  {
    "username": "fares_roj"
  },
  {
    "username": "safa_alazawea"
  },
  {
    "username": "s0fia87"
  },
  {
    "username": "shanty7554"
  },
  {
    "username": "mr.infinity_skylines"
  },
  {
    "username": "rafiq_hasan86"
  },
  {
    "username": "sagaradsul98"
  },
  {
    "username": "sapna9707"
  },
  {
    "username": "suchy_putry92"
  },
  {
    "username": "pareshdinani"
  },
  {
    "username": "faru_sweety_pie"
  },
  {
    "username": "yohannasalakory"
  },
  {
    "username": "m_athif"
  },
  {
    "username": "birjumarvaniya"
  },
  {
    "username": "__nishii7__"
  },
  {
    "username": "sukyingc"
  },
  {
    "username": "jawhernazary"
  },
  {
    "username": "itskuri88"
  },
  {
    "username": "ajitesh_sahu"
  },
  {
    "username": "heegiijavzandulam"
  },
  {
    "username": "mhalditalang"
  },
  {
    "username": "thandartun222888"
  },
  {
    "username": "jessedoster"
  },
  {
    "username": "christianmochilero"
  },
  {
    "username": "nhinhinheo"
  },
  {
    "username": "juliar_ra"
  },
  {
    "username": "abis_ali_jafri"
  },
  {
    "username": "nash_ramli"
  },
  {
    "username": "fame_girl123454"
  },
  {
    "username": "saurabhkshatriya01"
  },
  {
    "username": "official__awesome"
  },
  {
    "username": "mark_amged"
  },
  {
    "username": "mariam.asnaoui"
  },
  {
    "username": "anaahita_vverma"
  },
  {
    "username": "mrshubh101"
  },
  {
    "username": "ankitkumar1991"
  },
  {
    "username": "bavafaiz"
  },
  {
    "username": "rudresh__deore"
  },
  {
    "username": "mynayan"
  },
  {
    "username": "yassiiiiir"
  },
  {
    "username": "raman_k9"
  },
  {
    "username": "ayaz_gulljii"
  },
  {
    "username": "waismohdquraishi"
  },
  {
    "username": "babu9800860077"
  },
  {
    "username": "anamx12"
  },
  {
    "username": "kamlesdhangar0"
  },
  {
    "username": "ali_abd_alsaheb"
  },
  {
    "username": "skale5657"
  },
  {
    "username": "joshi_care"
  },
  {
    "username": "deiiba143"
  },
  {
    "username": "the_aluxer"
  },
  {
    "username": "jonathan.sepulveda.9638718"
  },
  {
    "username": "hairavat"
  },
  {
    "username": "sarahab_97"
  },
  {
    "username": "yoonhaefany1989"
  },
  {
    "username": "gamaileh12"
  },
  {
    "username": "jhraj"
  },
  {
    "username": "abubakarupkey"
  },
  {
    "username": "hmada.dawod.z9"
  },
  {
    "username": "shadabh206"
  },
  {
    "username": "extraordinary_2001"
  },
  {
    "username": "danielalbertoacuna"
  },
  {
    "username": "sammy_leeds_786"
  },
  {
    "username": "devyanibogam"
  },
  {
    "username": "kekudvr143"
  },
  {
    "username": "sattarahmadi4"
  },
  {
    "username": "raveendrathalla"
  },
  {
    "username": "aishkolhar"
  },
  {
    "username": "jashandeep7942"
  },
  {
    "username": "enlaankaanrn"
  },
  {
    "username": "thakkar_dhaval3348"
  },
  {
    "username": "seventytwolbs"
  },
  {
    "username": "aqa_eldar202"
  },
  {
    "username": "ghafar_hijran"
  },
  {
    "username": "d_u_d_u"
  },
  {
    "username": "adeelabdullah8"
  },
  {
    "username": "justanotherfollowerr"
  },
  {
    "username": "jhasikiranianu0408"
  },
  {
    "username": "abid_solanki"
  },
  {
    "username": "lokdeep_27"
  },
  {
    "username": "ameerh21345"
  },
  {
    "username": "rose___________________"
  },
  {
    "username": "asif_pinjari"
  },
  {
    "username": "nishad_sagar"
  },
  {
    "username": "ayan_6khan"
  },
  {
    "username": "edwardsannah"
  },
  {
    "username": "pinkabhaiya"
  },
  {
    "username": "sazedulsaju88"
  },
  {
    "username": "bw_aant"
  },
  {
    "username": "ramdayaldhaker"
  },
  {
    "username": "aman_sharma00"
  },
  {
    "username": "aliraza.malik147"
  },
  {
    "username": "ausafumer"
  },
  {
    "username": "r.k_boyss"
  },
  {
    "username": "ayshamubashirafarooque"
  },
  {
    "username": "teteybinmaqasba99_"
  },
  {
    "username": "sandeepb_bhati"
  },
  {
    "username": "kumar26586"
  },
  {
    "username": "3_meow"
  },
  {
    "username": "raju_hiddenwood_mao"
  },
  {
    "username": "jvr51112"
  },
  {
    "username": "asif72622"
  },
  {
    "username": "sathyagayatri"
  },
  {
    "username": "poojasingh7274"
  },
  {
    "username": "arijit_messi"
  },
  {
    "username": "paul_verified"
  },
  {
    "username": "brajesh_tomar"
  },
  {
    "username": "narendran_narendran"
  },
  {
    "username": "vickybhatiya"
  },
  {
    "username": "vinayka163"
  },
  {
    "username": "indahhardianti5"
  },
  {
    "username": "tasiaziz1"
  },
  {
    "username": "repoper_baby_"
  },
  {
    "username": "sidiquiaslam"
  },
  {
    "username": "susmita_haldar"
  },
  {
    "username": "jayeshjp09"
  },
  {
    "username": "ganesh.roy.739326"
  },
  {
    "username": "hiren_amin"
  },
  {
    "username": "mayur.shevate"
  },
  {
    "username": "usman_za"
  },
  {
    "username": "zyk22"
  },
  {
    "username": "chloe.peuke"
  },
  {
    "username": "tabzz.w"
  },
  {
    "username": "nidhi_parvatikar"
  },
  {
    "username": "chua_anne_"
  },
  {
    "username": "love_kids786"
  },
  {
    "username": "harshissar"
  },
  {
    "username": "sadiashona"
  },
  {
    "username": "puja_princess92"
  },
  {
    "username": "nitashilimkar"
  },
  {
    "username": "sbagade733"
  },
  {
    "username": "hardikzala42"
  },
  {
    "username": "sweat_up_and_danse"
  },
  {
    "username": "realshaikhaslam"
  },
  {
    "username": "sultan.jhajj"
  },
  {
    "username": "vicky_golhar"
  },
  {
    "username": "shuhair05"
  },
  {
    "username": "mr_marjan_mohsin"
  },
  {
    "username": "moiz.kw"
  },
  {
    "username": "harsh_1403"
  },
  {
    "username": "k_r_u_t_zzzzz"
  },
  {
    "username": "prajapati_harshil"
  },
  {
    "username": "deneel_patel"
  },
  {
    "username": "_maddyy_1203_"
  },
  {
    "username": "happyy_777"
  },
  {
    "username": "dalip_chumber"
  },
  {
    "username": "mukun.p"
  },
  {
    "username": "vinaysinghchundawat"
  },
  {
    "username": "palay_khan"
  },
  {
    "username": "govi.raut"
  },
  {
    "username": "mistrybhavesh3077"
  },
  {
    "username": "shaikh_saher"
  },
  {
    "username": "kevin_umariya"
  },
  {
    "username": "hmerchant_72"
  },
  {
    "username": "wasim_chipade"
  },
  {
    "username": "dinesh_bulchandani"
  },
  {
    "username": "beardoyt"
  },
  {
    "username": "quicksnacking"
  },
  {
    "username": "suraj_24_11"
  },
  {
    "username": "izhann_"
  },
  {
    "username": "ebrahimred"
  },
  {
    "username": "aiqaz__c"
  },
  {
    "username": "dharmesh_krishna"
  },
  {
    "username": "ibrahimg102"
  },
  {
    "username": "burhanuddin009"
  },
  {
    "username": "happiness_virus_"
  },
  {
    "username": "naffuvaghji"
  },
  {
    "username": "huzaifa_badshah"
  },
  {
    "username": "kartikkaul_"
  },
  {
    "username": "khan7757"
  },
  {
    "username": "abdul_moin49"
  },
  {
    "username": "rohann_sk"
  },
  {
    "username": "jadhavandy"
  },
  {
    "username": "absarsayyed"
  },
  {
    "username": "umarhegde"
  },
  {
    "username": "_u_m_x_i_r_"
  },
  {
    "username": "perfect_khan01"
  },
  {
    "username": "_x_ismail__x"
  },
  {
    "username": "ammar_thokan"
  },
  {
    "username": "gagan.rajput.9803"
  },
  {
    "username": "_altmsh"
  },
  {
    "username": "_zennie_267"
  },
  {
    "username": "india_travel_company"
  },
  {
    "username": "iffatthokan168"
  },
  {
    "username": "ranveerdeshmukh97"
  },
  {
    "username": "soham_badhe03"
  },
  {
    "username": "shashu_devil"
  },
  {
    "username": "abhij.e_e.t"
  },
  {
    "username": "dreamerbabe100"
  },
  {
    "username": "moiz_iamunited"
  },
  {
    "username": "saeed_89_"
  },
  {
    "username": "vfd9"
  },
  {
    "username": "drfatima_shaikh"
  },
  {
    "username": "soni_dhawal_"
  },
  {
    "username": "umair.shaikh.16718"
  },
  {
    "username": "abdul_sayyed123"
  },
  {
    "username": "taru_shaikh"
  },
  {
    "username": "jacked_wolf"
  },
  {
    "username": "sana_sjs"
  },
  {
    "username": "vikram___thakur"
  },
  {
    "username": "is1874389"
  },
  {
    "username": "awestruck_pics"
  },
  {
    "username": "jigar26"
  },
  {
    "username": "happyyash87"
  },
  {
    "username": "the_ashwin_nair"
  },
  {
    "username": "iffat_s"
  },
  {
    "username": "speedy_buggy_23"
  },
  {
    "username": "sachin.1003"
  },
  {
    "username": "khaled_dubai2"
  },
  {
    "username": "harsh117"
  },
  {
    "username": "ashwin.peter.73"
  },
  {
    "username": "safir_pathan"
  },
  {
    "username": "praasadd007"
  },
  {
    "username": "_kj_06"
  },
  {
    "username": "saifu_1996"
  },
  {
    "username": "mubininamdar"
  },
  {
    "username": "khushal_jagtap"
  },
  {
    "username": "squareoneprod"
  },
  {
    "username": "afnankazi786"
  },
  {
    "username": "kushtin_001"
  },
  {
    "username": "harisbagwan"
  },
  {
    "username": "farisallayl"
  },
  {
    "username": "insta_yjay"
  },
  {
    "username": "izcheeseburger"
  },
  {
    "username": "nerdo2345"
  },
  {
    "username": "memes_arena_na_"
  },
  {
    "username": "adi_perfectionist"
  }
]
